COPYING
README.md
adf2pdf.py
setup.cfg
setup.py
adf2pdf.egg-info/PKG-INFO
adf2pdf.egg-info/SOURCES.txt
adf2pdf.egg-info/dependency_links.txt
adf2pdf.egg-info/entry_points.txt
adf2pdf.egg-info/requires.txt
adf2pdf.egg-info/top_level.txt