Metadata-Version: 2.1
Name: adf2pdf
Version: 0.8.2
Summary: Automate the workflow around ADF scanning, OCR and PDF creation
Home-page: https://github.com/gsauthof/adf2pdf
Author: Georg Sauthoff
Author-email: mail@gms.tf
License: UNKNOWN
Project-URL: Bug Reports, https://github.com/gsauthof/adf2pdf/issues
Project-URL: Say Thanks!, https://gms.tf
Project-URL: Source, https://github.com/gsauthof/adf2pdf
Keywords: adf scanning sane duplex-scanning ocr tesseract pdf
Platform: UNKNOWN
Classifier: Development Status :: 5 - Production/Stable
Classifier: Intended Audience :: End Users/Desktop
Classifier: Topic :: Multimedia :: Graphics :: Capture :: Scanners
Classifier: License :: OSI Approved :: GNU General Public License v3 or later (GPLv3+)
Classifier: Programming Language :: Python :: 3
Classifier: Programming Language :: Python :: 3.6
Classifier: Programming Language :: Python :: 3.7
Classifier: Programming Language :: Python :: 3.8
Classifier: Programming Language :: Python :: 3.9
Requires-Python: >=3
